sharedcollections/__init__.py
sharedcollections/queue.py
sharedcollections/version.py
SharedCollections-0.0.2.dist-info/LICENSE
SharedCollections-0.0.2.dist-info/METADATA
SharedCollections-0.0.2.dist-info/WHEEL
SharedCollections-0.0.2.dist-info/top_level.txt
SharedCollections-0.0.2.dist-info/RECORD
