Metadata-Version: 2.1
Name: SharedCollections
Version: 0.0.2
Summary: SharedCollections contains some commonly used data structured collections, which can be accessed among some multiple access manager.
Home-page: https://github.com/antaripchatterjee/SharedCollections
Author: Antarip Chatterjee
Author-email: antarip.chatterjee22@gmail.com
License: MIT
Platform: UNKNOWN
Classifier: License :: OSI Approved :: MIT License
Classifier: Operating System :: OS Independent
Classifier: Programming Language :: Python :: 3.5
Classifier: Environment :: Console
Classifier: Development Status :: 3 - Alpha
Classifier: Intended Audience :: Developers
Classifier: Intended Audience :: Education
Classifier: Topic :: Education
Classifier: Topic :: Software Development
